limit_order_sdk/__init__.py
limit_order_sdk/address.py
limit_order_sdk/constants.py
limit_order_sdk/validations.py
limit_order_sdk/api/__init__.py
limit_order_sdk/api/api.py
limit_order_sdk/api/constants.py
limit_order_sdk/api/custom_types.py
limit_order_sdk/api/errors.py
limit_order_sdk/api/pager.py
limit_order_sdk/api/connector/__init__.py
limit_order_sdk/api/connector/http/__init__.py
limit_order_sdk/api/connector/http/fetch_provider.py
limit_order_sdk/api/connector/http/http_provider.py
limit_order_sdk/libs/__init__.py
limit_order_sdk/libs/byte_utils/__init__.py
limit_order_sdk/libs/byte_utils/bit_mask.py
limit_order_sdk/libs/byte_utils/bn.py
limit_order_sdk/libs/byte_utils/bytes_builder.py
limit_order_sdk/libs/byte_utils/bytes_iter.py
limit_order_sdk/libs/byte_utils/constants.py
limit_order_sdk/libs/byte_utils/validations.py
limit_order_sdk/libs/byte_utils/utils/__init__.py
limit_order_sdk/libs/byte_utils/utils/as_bytes.py
limit_order_sdk/libs/byte_utils/utils/get_bytes_count.py
limit_order_sdk/libs/byte_utils/utils/zero_x_prefix.py
limit_order_sdk/limit_order/__init__.py
limit_order_sdk/limit_order/amounts.py
limit_order_sdk/limit_order/custom_types.py
limit_order_sdk/limit_order/extension.py
limit_order_sdk/limit_order/extension_builder.py
limit_order_sdk/limit_order/interaction.py
limit_order_sdk/limit_order/limit_order.py
limit_order_sdk/limit_order/maker_traits.py
limit_order_sdk/limit_order/taker_traits.py
limit_order_sdk/limit_order/eip712/__init__.py
limit_order_sdk/limit_order/eip712/domain.py
limit_order_sdk/limit_order/eip712/eip712_types.py
limit_order_sdk/limit_order/eip712/order_typed_data_buider.py
limit_order_sdk/limit_order_contract/AggregationRouterV6.abi.json
limit_order_sdk/limit_order_contract/__init__.py
limit_order_sdk/limit_order_contract/limit_order_contract.py
limit_order_sdk/rfq_order/__init__.py
limit_order_sdk/rfq_order/rfq_order.py
limit_order_sdk/utils/__init__.py
limit_order_sdk/utils/contract.py
limit_order_sdk-0.0.3.dist-info/METADATA
limit_order_sdk-0.0.3.dist-info/WHEEL
limit_order_sdk-0.0.3.dist-info/top_level.txt
limit_order_sdk-0.0.3.dist-info/RECORD
