Metadata-Version: 2.1
Name: limit-order-sdk
Version: 0.0.3
Summary: 1inch Limit Order Protocol v4 SDK
Home-page: https://github.com/1inch/limit-order-sdk-py
Author: 1inch, dodgervl
Author-email: 
Classifier: Programming Language :: Python :: 3
Classifier: Programming Language :: Python :: 3.11
Classifier: License :: OSI Approved :: MIT License
Classifier: Operating System :: OS Independent
Requires-Python: >=3.11, <3.15
Requires-Dist: web3
Requires-Dist: requests
Provides-Extra: dev
Requires-Dist: pytest ; extra == 'dev'
Requires-Dist: twine ; extra == 'dev'
Requires-Dist: build ; extra == 'dev'
